redditmonitor/__init__.py
redditmonitor/config.py
redditmonitor/monitor.py
redditmonitor-0.2.1.dist-info/LICENSE
redditmonitor-0.2.1.dist-info/METADATA
redditmonitor-0.2.1.dist-info/WHEEL
redditmonitor-0.2.1.dist-info/entry_points.txt
redditmonitor-0.2.1.dist-info/top_level.txt
redditmonitor-0.2.1.dist-info/RECORD
